odoo/addons/project_timeline_hr_timesheet/README.rst
odoo/addons/project_timeline_hr_timesheet/__init__.py
odoo/addons/project_timeline_hr_timesheet/__manifest__.py
odoo/addons/project_timeline_hr_timesheet/i18n/de.po
odoo/addons/project_timeline_hr_timesheet/i18n/es.po
odoo/addons/project_timeline_hr_timesheet/i18n/fr.po
odoo/addons/project_timeline_hr_timesheet/i18n/he.po
odoo/addons/project_timeline_hr_timesheet/i18n/it.po
odoo/addons/project_timeline_hr_timesheet/i18n/project_timeline_hr_timesheet.pot
odoo/addons/project_timeline_hr_timesheet/readme/CONTRIBUTORS.md
odoo/addons/project_timeline_hr_timesheet/readme/DESCRIPTION.md
odoo/addons/project_timeline_hr_timesheet/static/description/icon.png
odoo/addons/project_timeline_hr_timesheet/static/description/index.html
odoo/addons/project_timeline_hr_timesheet/static/src/scss/project_timeline_hr_timesheet.scss
odoo/addons/project_timeline_hr_timesheet/views/project_task_view.xml
odoo_addon_project_timeline_hr_timesheet-18.0.1.0.0.2.dist-info/METADATA
odoo_addon_project_timeline_hr_timesheet-18.0.1.0.0.2.dist-info/WHEEL
odoo_addon_project_timeline_hr_timesheet-18.0.1.0.0.2.dist-info/top_level.txt
odoo_addon_project_timeline_hr_timesheet-18.0.1.0.0.2.dist-info/RECORD
